MANIFEST.in
README.txt
setup.py
PAC_tool.egg-info/PKG-INFO
PAC_tool.egg-info/SOURCES.txt
PAC_tool.egg-info/dependency_links.txt
PAC_tool.egg-info/requires.txt
PAC_tool.egg-info/top_level.txt
pactool/__init__.py
pactool/association_test.py
pactool/frequencies.py
pactool/getinfo.py
pactool/hwe.py
pactool/kor.py
pactool/ld.py
pactool/multitools.py
pactool/pactool.py