Metadata-Version: 1.0
Name: PAC-tool
Version: 1.0.6a
Summary: This is our little project for GWAS
Home-page: https://github.com/pnatsi/PACtool
Author: Akis, Christina, Paschalis
Author-email: pnatsidis@hotmail.com
License: MIT
Keywords: project python linux gwas bioinfo-grad
Platform: UNKNOWN
